<?xml version="1.0" encoding="utf-8"?>
<ArrayOfSThought xmlns:xsi="http://www.w3.org/2001/XMLSchema-instance" xmlns:xsd="http://www.w3.org/2001/XMLSchema">
  <sThought>
    <index>0</index>
    <label>BrainSim</label>
  </sThought>
  <sThought>
    <index>1</index>
    <label>AvailableModule</label>
  </sThought>
  <sThought>
    <index>2</index>
    <label>is-a</label>
  </sThought>
  <sThought>
    <index>3</index>
    <label>unl_e576602f</label>
    <source>1</source>
    <linkType>2</linkType>
    <target>0</target>
  </sThought>
  <sThought>
    <index>4</index>
    <label>ActiveModule</label>
  </sThought>
  <sThought>
    <index>5</index>
    <label>unl_8747589e</label>
    <source>4</source>
    <linkType>2</linkType>
    <target>0</target>
  </sThought>
  <sThought>
    <index>6</index>
    <label>DlgAttrib</label>
  </sThought>
  <sThought>
    <index>7</index>
    <label>unl_07ee4c53</label>
    <source>6</source>
    <linkType>2</linkType>
    <target>0</target>
  </sThought>
  <sThought>
    <index>8</index>
    <label>ModuleUKS</label>
  </sThought>
  <sThought>
    <index>9</index>
    <label>unl_b2c2e21d</label>
    <source>8</source>
    <linkType>2</linkType>
    <target>1</target>
  </sThought>
  <sThought>
    <index>10</index>
    <label>ModuleUKSStatement</label>
  </sThought>
  <sThought>
    <index>11</index>
    <label>unl_1bada1fb</label>
    <source>10</source>
    <linkType>2</linkType>
    <target>1</target>
  </sThought>
  <sThought>
    <index>12</index>
    <label>ModuleAddCounts</label>
  </sThought>
  <sThought>
    <index>13</index>
    <label>unl_c5605f66</label>
    <source>12</source>
    <linkType>2</linkType>
    <target>1</target>
  </sThought>
  <sThought>
    <index>14</index>
    <label>ModuleAttributeBubble</label>
  </sThought>
  <sThought>
    <index>15</index>
    <label>unl_5dcd22ac</label>
    <source>14</source>
    <linkType>2</linkType>
    <target>1</target>
  </sThought>
  <sThought>
    <index>16</index>
    <label>ModuleBalanceTree</label>
  </sThought>
  <sThought>
    <index>17</index>
    <label>unl_2e3deca2</label>
    <source>16</source>
    <linkType>2</linkType>
    <target>1</target>
  </sThought>
  <sThought>
    <index>18</index>
    <label>ModuleClassCreate</label>
  </sThought>
  <sThought>
    <index>19</index>
    <label>unl_b5d8644e</label>
    <source>18</source>
    <linkType>2</linkType>
    <target>1</target>
  </sThought>
  <sThought>
    <index>20</index>
    <label>ModuleEmpty</label>
  </sThought>
  <sThought>
    <index>21</index>
    <label>unl_8bc6f77c</label>
    <source>20</source>
    <linkType>2</linkType>
    <target>1</target>
  </sThought>
  <sThought>
    <index>22</index>
    <label>ModuleGPTInfo</label>
  </sThought>
  <sThought>
    <index>23</index>
    <label>unl_47eecc4b</label>
    <source>22</source>
    <linkType>2</linkType>
    <target>1</target>
  </sThought>
  <sThought>
    <index>24</index>
    <label>ModuleOnlineInfo</label>
  </sThought>
  <sThought>
    <index>25</index>
    <label>unl_91a22b57</label>
    <source>24</source>
    <linkType>2</linkType>
    <target>1</target>
  </sThought>
  <sThought>
    <index>26</index>
    <label>ModuleRemoveRedundancy</label>
  </sThought>
  <sThought>
    <index>27</index>
    <label>unl_5c28586b</label>
    <source>26</source>
    <linkType>2</linkType>
    <target>1</target>
  </sThought>
  <sThought>
    <index>28</index>
    <label>ModuleShowGraph</label>
  </sThought>
  <sThought>
    <index>29</index>
    <label>unl_7f37995a</label>
    <source>28</source>
    <linkType>2</linkType>
    <target>1</target>
  </sThought>
  <sThought>
    <index>30</index>
    <label>ModuleStressTest</label>
  </sThought>
  <sThought>
    <index>31</index>
    <label>unl_3a1f2964</label>
    <source>30</source>
    <linkType>2</linkType>
    <target>1</target>
  </sThought>
  <sThought>
    <index>32</index>
    <label>ModuleText</label>
  </sThought>
  <sThought>
    <index>33</index>
    <label>unl_9b154f2e</label>
    <source>32</source>
    <linkType>2</linkType>
    <target>1</target>
  </sThought>
  <sThought>
    <index>34</index>
    <label>ModuleUKSQuery</label>
  </sThought>
  <sThought>
    <index>35</index>
    <label>unl_80a732a2</label>
    <source>34</source>
    <linkType>2</linkType>
    <target>1</target>
  </sThought>
  <sThought>
    <index>36</index>
    <label>ModuleWord</label>
  </sThought>
  <sThought>
    <index>37</index>
    <label>unl_b1d4e4ac</label>
    <source>36</source>
    <linkType>2</linkType>
    <target>1</target>
  </sThought>
  <sThought>
    <index>38</index>
    <label>ModuleAction</label>
  </sThought>
  <sThought>
    <index>39</index>
    <label>unl_b71f89f6</label>
    <source>38</source>
    <linkType>2</linkType>
    <target>1</target>
  </sThought>
  <sThought>
    <index>40</index>
    <label>ModuleAddToMentalModel</label>
  </sThought>
  <sThought>
    <index>41</index>
    <label>unl_4c38978d</label>
    <source>40</source>
    <linkType>2</linkType>
    <target>1</target>
  </sThought>
  <sThought>
    <index>42</index>
    <label>ModuleAttention</label>
  </sThought>
  <sThought>
    <index>43</index>
    <label>unl_be98a994</label>
    <source>42</source>
    <linkType>2</linkType>
    <target>1</target>
  </sThought>
  <sThought>
    <index>44</index>
    <label>ModuleAttentionS</label>
  </sThought>
  <sThought>
    <index>45</index>
    <label>unl_82e77dc1</label>
    <source>44</source>
    <linkType>2</linkType>
    <target>1</target>
  </sThought>
  <sThought>
    <index>46</index>
    <label>ModuleMentalModel</label>
  </sThought>
  <sThought>
    <index>47</index>
    <label>unl_db92610a</label>
    <source>46</source>
    <linkType>2</linkType>
    <target>1</target>
  </sThought>
  <sThought>
    <index>48</index>
    <label>ModuleSoundIn</label>
  </sThought>
  <sThought>
    <index>49</index>
    <label>unl_52f71e2a</label>
    <source>48</source>
    <linkType>2</linkType>
    <target>1</target>
  </sThought>
  <sThought>
    <index>50</index>
    <label>ModuleSoundOut</label>
  </sThought>
  <sThought>
    <index>51</index>
    <label>unl_ecaf6d55</label>
    <source>50</source>
    <linkType>2</linkType>
    <target>1</target>
  </sThought>
  <sThought>
    <index>52</index>
    <label>ModuleTextIn</label>
  </sThought>
  <sThought>
    <index>53</index>
    <label>unl_361b40f4</label>
    <source>52</source>
    <linkType>2</linkType>
    <target>1</target>
  </sThought>
  <sThought>
    <index>54</index>
    <label>ModuleWellBeing</label>
  </sThought>
  <sThought>
    <index>55</index>
    <label>unl_e4c34ebe</label>
    <source>54</source>
    <linkType>2</linkType>
    <target>1</target>
  </sThought>
  <sThought>
    <index>56</index>
    <label>module_add_statement.py</label>
  </sThought>
  <sThought>
    <index>57</index>
    <label>unl_3f29f269</label>
    <source>56</source>
    <linkType>2</linkType>
    <target>1</target>
  </sThought>
  <sThought>
    <index>58</index>
    <label>module_uks_tree.py</label>
  </sThought>
  <sThought>
    <index>59</index>
    <label>unl_66cfb144</label>
    <source>58</source>
    <linkType>2</linkType>
    <target>1</target>
  </sThought>
  <sThought>
    <index>60</index>
    <label>ModuleUKS0</label>
  </sThought>
  <sThought>
    <index>61</index>
    <label>unl_c9e5c928</label>
    <source>60</source>
    <linkType>2</linkType>
    <target>4</target>
  </sThought>
  <sThought>
    <index>62</index>
    <label>ModuleTextIn0</label>
  </sThought>
  <sThought>
    <index>63</index>
    <label>unl_fce00bdf</label>
    <source>62</source>
    <linkType>2</linkType>
    <target>4</target>
  </sThought>
  <sThought>
    <index>64</index>
    <label>ModuleUKS1</label>
  </sThought>
  <sThought>
    <index>65</index>
    <label>unl_b814ddf1</label>
    <source>64</source>
    <linkType>2</linkType>
    <target>4</target>
  </sThought>
  <sThought>
    <index>66</index>
    <label>Open</label>
    <V xsi:type="xsd:string">True</V>
  </sThought>
  <sThought>
    <index>67</index>
    <label>unl_26e698e0</label>
    <source>66</source>
    <linkType>2</linkType>
    <target>6</target>
  </sThought>
  <sThought>
    <index>68</index>
    <label>DlgWindow</label>
    <V xsi:type="xsd:string">1022x917+1157+78</V>
  </sThought>
  <sThought>
    <index>69</index>
    <label>unl_e8aa6ddb</label>
    <source>68</source>
    <linkType>2</linkType>
    <target>6</target>
  </sThought>
  <sThought>
    <index>70</index>
    <label>Root</label>
    <V xsi:type="xsd:string">Language</V>
  </sThought>
  <sThought>
    <index>71</index>
    <label>unl_98821312</label>
    <source>70</source>
    <linkType>2</linkType>
    <target>6</target>
  </sThought>
  <sThought>
    <index>72</index>
    <label>Open0</label>
    <V xsi:type="xsd:string"></V>
  </sThought>
  <sThought>
    <index>73</index>
    <label>unl_47762bb7</label>
    <source>72</source>
    <linkType>2</linkType>
    <target>6</target>
  </sThought>
  <sThought>
    <index>74</index>
    <label>DlgWindow0</label>
    <V xsi:type="xsd:string">530x300+1107+122</V>
  </sThought>
  <sThought>
    <index>75</index>
    <label>unl_56256c82</label>
    <source>74</source>
    <linkType>2</linkType>
    <target>6</target>
  </sThought>
  <sThought>
    <index>76</index>
    <label>Open1</label>
    <V xsi:type="xsd:string"></V>
  </sThought>
  <sThought>
    <index>77</index>
    <label>unl_50abda89</label>
    <source>76</source>
    <linkType>2</linkType>
    <target>6</target>
  </sThought>
  <sThought>
    <index>78</index>
    <label>DlgWindow1</label>
    <V xsi:type="xsd:string">530x550+1114+440</V>
  </sThought>
  <sThought>
    <index>79</index>
    <label>unl_3a2acbfa</label>
    <source>78</source>
    <linkType>2</linkType>
    <target>6</target>
  </sThought>
  <sThought>
    <index>80</index>
    <label>Open2</label>
    <V xsi:type="xsd:string">True</V>
  </sThought>
  <sThought>
    <index>81</index>
    <label>unl_1cbb5097</label>
    <source>80</source>
    <linkType>2</linkType>
    <target>6</target>
  </sThought>
  <sThought>
    <index>82</index>
    <label>DlgWindow2</label>
    <V xsi:type="xsd:string">598x300+312+142</V>
  </sThought>
  <sThought>
    <index>83</index>
    <label>unl_3947d109</label>
    <source>82</source>
    <linkType>2</linkType>
    <target>6</target>
  </sThought>
  <sThought>
    <index>84</index>
    <label>ExpandAll</label>
    <V xsi:type="xsd:string">Language</V>
  </sThought>
  <sThought>
    <index>85</index>
    <label>unl_9e381dfe</label>
    <source>84</source>
    <linkType>2</linkType>
    <target>6</target>
  </sThought>
  <sThought>
    <index>86</index>
    <label>Open3</label>
    <V xsi:type="xsd:string">True</V>
  </sThought>
  <sThought>
    <index>87</index>
    <label>unl_ac05f110</label>
    <source>86</source>
    <linkType>2</linkType>
    <target>6</target>
  </sThought>
  <sThought>
    <index>88</index>
    <label>DlgWindow3</label>
    <V xsi:type="xsd:string">800x915+923+78</V>
  </sThought>
  <sThought>
    <index>89</index>
    <label>unl_4cb24f6c</label>
    <source>88</source>
    <linkType>2</linkType>
    <target>6</target>
  </sThought>
  <sThought>
    <index>90</index>
    <label>Root0</label>
    <V xsi:type="xsd:string">Unknown</V>
  </sThought>
  <sThought>
    <index>91</index>
    <label>unl_176ca386</label>
    <source>90</source>
    <linkType>2</linkType>
    <target>6</target>
  </sThought>
  <sThought>
    <index>92</index>
    <label>RootHistory</label>
    <V xsi:type="xsd:string">Unknown</V>
  </sThought>
  <sThought>
    <index>93</index>
    <label>unl_04219ea4</label>
    <source>92</source>
    <linkType>2</linkType>
    <target>6</target>
  </sThought>
  <sThought>
    <index>94</index>
    <label>ExpandAll0</label>
    <V xsi:type="xsd:string">Unknown</V>
  </sThought>
  <sThought>
    <index>95</index>
    <label>unl_aafaf36c</label>
    <source>94</source>
    <linkType>2</linkType>
    <target>6</target>
  </sThought>
  <sThought>
    <index>96</index>
    <label>hasProperty</label>
  </sThought>
  <sThought>
    <index>97</index>
    <label>isTransitive</label>
  </sThought>
  <sThought>
    <index>98</index>
    <label>unl_90a9e4dd</label>
    <source>2</source>
    <linkType>96</linkType>
    <target>97</target>
  </sThought>
  <sThought>
    <index>99</index>
    <label>inheritable</label>
  </sThought>
  <sThought>
    <index>100</index>
    <label>unl_0a165c0b</label>
    <source>2</source>
    <linkType>96</linkType>
    <target>99</target>
  </sThought>
  <sThought>
    <index>101</index>
    <label>unl_aaf10caf</label>
    <source>60</source>
    <linkType>2</linkType>
    <target>8</target>
  </sThought>
  <sThought>
    <index>102</index>
    <label>unl_80b0a971</label>
    <source>64</source>
    <linkType>2</linkType>
    <target>8</target>
  </sThought>
  <sThought>
    <index>103</index>
    <label>unl_485ba407</label>
    <source>62</source>
    <linkType>2</linkType>
    <target>52</target>
  </sThought>
  <sThought>
    <index>104</index>
    <label>hasAttribute</label>
  </sThought>
  <sThought>
    <index>105</index>
    <label>unl_6936dd7f</label>
    <source>60</source>
    <linkType>104</linkType>
    <target>66</target>
  </sThought>
  <sThought>
    <index>106</index>
    <label>unl_124741f7</label>
    <source>60</source>
    <linkType>104</linkType>
    <target>68</target>
  </sThought>
  <sThought>
    <index>107</index>
    <label>unl_e0bb3282</label>
    <source>60</source>
    <linkType>104</linkType>
    <target>70</target>
  </sThought>
  <sThought>
    <index>108</index>
    <label>unl_3201515e</label>
    <source>60</source>
    <linkType>104</linkType>
    <target>84</target>
  </sThought>
  <sThought>
    <index>109</index>
    <label>unl_dc918199</label>
    <source>62</source>
    <linkType>104</linkType>
    <target>80</target>
  </sThought>
  <sThought>
    <index>110</index>
    <label>unl_8aae4db3</label>
    <source>62</source>
    <linkType>104</linkType>
    <target>82</target>
  </sThought>
  <sThought>
    <index>111</index>
    <label>unl_0ee5474e</label>
    <source>64</source>
    <linkType>104</linkType>
    <target>86</target>
  </sThought>
  <sThought>
    <index>112</index>
    <label>unl_fdebc4c3</label>
    <source>64</source>
    <linkType>104</linkType>
    <target>88</target>
  </sThought>
  <sThought>
    <index>113</index>
    <label>unl_f813497a</label>
    <source>64</source>
    <linkType>104</linkType>
    <target>90</target>
  </sThought>
  <sThought>
    <index>114</index>
    <label>unl_81fd6d04</label>
    <source>64</source>
    <linkType>104</linkType>
    <target>92</target>
  </sThought>
  <sThought>
    <index>115</index>
    <label>unl_04ba9639</label>
    <source>64</source>
    <linkType>104</linkType>
    <target>94</target>
  </sThought>
  <sThought>
    <index>116</index>
    <label>Thought</label>
  </sThought>
  <sThought>
    <index>117</index>
    <label>LinkType</label>
  </sThought>
  <sThought>
    <index>118</index>
    <label>unl_2276d99d</label>
    <source>117</source>
    <linkType>2</linkType>
    <target>116</target>
  </sThought>
  <sThought>
    <index>119</index>
    <label>Unknown</label>
  </sThought>
  <sThought>
    <index>120</index>
    <label>unl_d6e00512</label>
    <source>119</source>
    <linkType>2</linkType>
    <target>116</target>
  </sThought>
  <sThought>
    <index>121</index>
    <label>Abstract</label>
  </sThought>
  <sThought>
    <index>122</index>
    <label>unl_4239c708</label>
    <source>121</source>
    <linkType>2</linkType>
    <target>116</target>
  </sThought>
  <sThought>
    <index>123</index>
    <label>Object</label>
  </sThought>
  <sThought>
    <index>124</index>
    <label>unl_bc0992f6</label>
    <source>123</source>
    <linkType>2</linkType>
    <target>116</target>
  </sThought>
  <sThought>
    <index>125</index>
    <label>Action</label>
  </sThought>
  <sThought>
    <index>126</index>
    <label>unl_500b01e2</label>
    <source>125</source>
    <linkType>2</linkType>
    <target>116</target>
  </sThought>
  <sThought>
    <index>127</index>
    <label>Link</label>
  </sThought>
  <sThought>
    <index>128</index>
    <label>unl_711e339d</label>
    <source>127</source>
    <linkType>2</linkType>
    <target>116</target>
  </sThought>
  <sThought>
    <index>129</index>
    <label>Language</label>
  </sThought>
  <sThought>
    <index>130</index>
    <label>unl_a329d9c0</label>
    <source>129</source>
    <linkType>2</linkType>
    <target>116</target>
  </sThought>
  <sThought>
    <index>131</index>
    <label>unl_dd6853b9</label>
    <source>2</source>
    <linkType>2</linkType>
    <target>117</target>
  </sThought>
  <sThought>
    <index>132</index>
    <label>has-child</label>
  </sThought>
  <sThought>
    <index>133</index>
    <label>unl_784fd599</label>
    <source>132</source>
    <linkType>2</linkType>
    <target>117</target>
  </sThought>
  <sThought>
    <index>134</index>
    <label>inverseOf</label>
  </sThought>
  <sThought>
    <index>135</index>
    <label>unl_f03dfa6b</label>
    <source>134</source>
    <linkType>2</linkType>
    <target>117</target>
  </sThought>
  <sThought>
    <index>136</index>
    <label>unl_ca67c129</label>
    <source>96</source>
    <linkType>2</linkType>
    <target>117</target>
  </sThought>
  <sThought>
    <index>137</index>
    <label>is</label>
  </sThought>
  <sThought>
    <index>138</index>
    <label>unl_4652f7e2</label>
    <source>137</source>
    <linkType>2</linkType>
    <target>117</target>
  </sThought>
  <sThought>
    <index>139</index>
    <label>unl_9e288dd0</label>
    <source>104</source>
    <linkType>2</linkType>
    <target>117</target>
  </sThought>
  <sThought>
    <index>140</index>
    <label>can</label>
  </sThought>
  <sThought>
    <index>141</index>
    <label>unl_a5f3d68b</label>
    <source>140</source>
    <linkType>2</linkType>
    <target>117</target>
  </sThought>
  <sThought>
    <index>142</index>
    <label>mostRecent</label>
  </sThought>
  <sThought>
    <index>143</index>
    <label>unl_d9b1722a</label>
    <source>142</source>
    <linkType>2</linkType>
    <target>117</target>
  </sThought>
  <sThought>
    <index>144</index>
    <label>contains</label>
  </sThought>
  <sThought>
    <index>145</index>
    <label>unl_38b599b8</label>
    <source>144</source>
    <linkType>2</linkType>
    <target>117</target>
  </sThought>
  <sThought>
    <index>146</index>
    <label>is-part-of</label>
  </sThought>
  <sThought>
    <index>147</index>
    <label>unl_7c8b6773</label>
    <source>146</source>
    <linkType>2</linkType>
    <target>117</target>
  </sThought>
  <sThought>
    <index>148</index>
    <label>has</label>
  </sThought>
  <sThought>
    <index>149</index>
    <label>unl_bae57b43</label>
    <source>148</source>
    <linkType>2</linkType>
    <target>117</target>
  </sThought>
  <sThought>
    <index>150</index>
    <label>Property</label>
  </sThought>
  <sThought>
    <index>151</index>
    <label>unl_0645e033</label>
    <source>150</source>
    <linkType>2</linkType>
    <target>117</target>
  </sThought>
  <sThought>
    <index>152</index>
    <label>ClauseType</label>
  </sThought>
  <sThought>
    <index>153</index>
    <label>unl_7beabfaa</label>
    <source>152</source>
    <linkType>2</linkType>
    <target>117</target>
  </sThought>
  <sThought>
    <index>154</index>
    <label>Comparison</label>
  </sThought>
  <sThought>
    <index>155</index>
    <label>unl_4718185c</label>
    <source>154</source>
    <linkType>2</linkType>
    <target>117</target>
  </sThought>
  <sThought>
    <index>156</index>
    <label>means</label>
  </sThought>
  <sThought>
    <index>157</index>
    <label>unl_a4ddf6f1</label>
    <source>156</source>
    <linkType>2</linkType>
    <target>117</target>
  </sThought>
  <sThought>
    <index>158</index>
    <label>w:has</label>
  </sThought>
  <sThought>
    <index>159</index>
    <label>unl_2c431c3a</label>
    <source>158</source>
    <linkType>2</linkType>
    <target>117</target>
  </sThought>
  <sThought>
    <index>160</index>
    <label>color</label>
  </sThought>
  <sThought>
    <index>161</index>
    <label>unl_c638053a</label>
    <source>160</source>
    <linkType>2</linkType>
    <target>121</target>
  </sThought>
  <sThought>
    <index>162</index>
    <label>number</label>
  </sThought>
  <sThought>
    <index>163</index>
    <label>unl_810210d6</label>
    <source>162</source>
    <linkType>2</linkType>
    <target>121</target>
  </sThought>
  <sThought>
    <index>164</index>
    <label>Phrase</label>
  </sThought>
  <sThought>
    <index>165</index>
    <label>unl_80d09039</label>
    <source>164</source>
    <linkType>2</linkType>
    <target>129</target>
  </sThought>
  <sThought>
    <index>166</index>
    <label>EnglishWord</label>
  </sThought>
  <sThought>
    <index>167</index>
    <label>unl_c40585bf</label>
    <source>166</source>
    <linkType>2</linkType>
    <target>129</target>
  </sThought>
  <sThought>
    <index>168</index>
    <label>SpanishWord</label>
  </sThought>
  <sThought>
    <index>169</index>
    <label>unl_47283dbc</label>
    <source>168</source>
    <linkType>2</linkType>
    <target>129</target>
  </sThought>
  <sThought>
    <index>170</index>
    <label>unl_b24872aa</label>
    <source>2</source>
    <linkType>96</linkType>
    <target>97</target>
  </sThought>
  <sThought>
    <index>171</index>
    <label>unl_b1119008</label>
    <source>2</source>
    <linkType>96</linkType>
    <target>99</target>
  </sThought>
  <sThought>
    <index>172</index>
    <label>unl_be6070be</label>
    <source>132</source>
    <linkType>134</linkType>
    <target>2</target>
  </sThought>
  <sThought>
    <index>173</index>
    <label>unl_443dfa7e</label>
    <source>144</source>
    <linkType>134</linkType>
    <target>146</target>
  </sThought>
  <sThought>
    <index>174</index>
    <label>hasDigit</label>
  </sThought>
  <sThought>
    <index>175</index>
    <label>unl_9c525bc1</label>
    <source>174</source>
    <linkType>2</linkType>
    <target>148</target>
  </sThought>
  <sThought>
    <index>176</index>
    <label>unl_13264993</label>
    <source>148</source>
    <linkType>96</linkType>
    <target>97</target>
  </sThought>
  <sThought>
    <index>177</index>
    <label>unl_97ddc89a</label>
    <source>148</source>
    <linkType>96</linkType>
    <target>99</target>
  </sThought>
  <sThought>
    <index>178</index>
    <label>isExclusive</label>
  </sThought>
  <sThought>
    <index>179</index>
    <label>unl_62a2e6f1</label>
    <source>178</source>
    <linkType>2</linkType>
    <target>150</target>
  </sThought>
  <sThought>
    <index>180</index>
    <label>unl_a2a6db33</label>
    <source>97</source>
    <linkType>2</linkType>
    <target>150</target>
  </sThought>
  <sThought>
    <index>181</index>
    <label>isInstance</label>
  </sThought>
  <sThought>
    <index>182</index>
    <label>unl_f0854646</label>
    <source>181</source>
    <linkType>2</linkType>
    <target>150</target>
  </sThought>
  <sThought>
    <index>183</index>
    <label>isCommutative</label>
  </sThought>
  <sThought>
    <index>184</index>
    <label>unl_cbd7fa5b</label>
    <source>183</source>
    <linkType>2</linkType>
    <target>150</target>
  </sThought>
  <sThought>
    <index>185</index>
    <label>allowMultiple</label>
  </sThought>
  <sThought>
    <index>186</index>
    <label>unl_a438f77b</label>
    <source>185</source>
    <linkType>2</linkType>
    <target>150</target>
  </sThought>
  <sThought>
    <index>187</index>
    <label>unl_8dea75a9</label>
    <source>99</source>
    <linkType>2</linkType>
    <target>150</target>
  </sThought>
  <sThought>
    <index>188</index>
    <label>isCondition</label>
  </sThought>
  <sThought>
    <index>189</index>
    <label>unl_cb14e8c4</label>
    <source>188</source>
    <linkType>2</linkType>
    <target>150</target>
  </sThought>
  <sThought>
    <index>190</index>
    <label>isResult</label>
  </sThought>
  <sThought>
    <index>191</index>
    <label>unl_7d7528c9</label>
    <source>190</source>
    <linkType>2</linkType>
    <target>150</target>
  </sThought>
  <sThought>
    <index>192</index>
    <label>IF</label>
  </sThought>
  <sThought>
    <index>193</index>
    <label>unl_0a528048</label>
    <source>192</source>
    <linkType>2</linkType>
    <target>152</target>
  </sThought>
  <sThought>
    <index>194</index>
    <label>BECAUSE</label>
  </sThought>
  <sThought>
    <index>195</index>
    <label>unl_d471af19</label>
    <source>194</source>
    <linkType>2</linkType>
    <target>152</target>
  </sThought>
  <sThought>
    <index>196</index>
    <label>AFTER</label>
  </sThought>
  <sThought>
    <index>197</index>
    <label>unl_9f408fd5</label>
    <source>196</source>
    <linkType>2</linkType>
    <target>152</target>
  </sThought>
  <sThought>
    <index>198</index>
    <label>BEFORE</label>
  </sThought>
  <sThought>
    <index>199</index>
    <label>unl_360ba6e2</label>
    <source>198</source>
    <linkType>2</linkType>
    <target>152</target>
  </sThought>
  <sThought>
    <index>200</index>
    <label>NXT</label>
  </sThought>
  <sThought>
    <index>201</index>
    <label>unl_f8a6a4e3</label>
    <source>200</source>
    <linkType>2</linkType>
    <target>152</target>
  </sThought>
  <sThought>
    <index>202</index>
    <label>VLU</label>
  </sThought>
  <sThought>
    <index>203</index>
    <label>unl_c7aa985c</label>
    <source>202</source>
    <linkType>2</linkType>
    <target>152</target>
  </sThought>
  <sThought>
    <index>204</index>
    <label>AND</label>
  </sThought>
  <sThought>
    <index>205</index>
    <label>unl_ce332cb2</label>
    <source>204</source>
    <linkType>2</linkType>
    <target>152</target>
  </sThought>
  <sThought>
    <index>206</index>
    <label>OR</label>
  </sThought>
  <sThought>
    <index>207</index>
    <label>unl_1233f134</label>
    <source>206</source>
    <linkType>2</linkType>
    <target>152</target>
  </sThought>
  <sThought>
    <index>208</index>
    <label>NOT</label>
  </sThought>
  <sThought>
    <index>209</index>
    <label>unl_8a1cc8ed</label>
    <source>208</source>
    <linkType>2</linkType>
    <target>152</target>
  </sThought>
  <sThought>
    <index>210</index>
    <label>NO</label>
  </sThought>
  <sThought>
    <index>211</index>
    <label>unl_9845f2cc</label>
    <source>210</source>
    <linkType>2</linkType>
    <target>152</target>
  </sThought>
  <sThought>
    <index>212</index>
    <label>FRST</label>
  </sThought>
  <sThought>
    <index>213</index>
    <label>unl_76b4e55b</label>
    <source>212</source>
    <linkType>2</linkType>
    <target>152</target>
  </sThought>
  <sThought>
    <index>214</index>
    <label>order</label>
  </sThought>
  <sThought>
    <index>215</index>
    <label>unl_da50d998</label>
    <source>214</source>
    <linkType>2</linkType>
    <target>154</target>
  </sThought>
  <sThought>
    <index>216</index>
    <label>greaterThan</label>
  </sThought>
  <sThought>
    <index>217</index>
    <label>unl_e9597ef3</label>
    <source>216</source>
    <linkType>2</linkType>
    <target>154</target>
  </sThought>
  <sThought>
    <index>218</index>
    <label>lessThan</label>
  </sThought>
  <sThought>
    <index>219</index>
    <label>unl_a7311494</label>
    <source>218</source>
    <linkType>2</linkType>
    <target>154</target>
  </sThought>
  <sThought>
    <index>220</index>
    <label>isSimilarTo</label>
  </sThought>
  <sThought>
    <index>221</index>
    <label>unl_026d1d10</label>
    <source>220</source>
    <linkType>2</linkType>
    <target>154</target>
  </sThought>
  <sThought>
    <index>222</index>
    <label>unl_767d09b7</label>
    <source>158</source>
    <linkType>156</linkType>
    <target>148</target>
  </sThought>
  <sThought>
    <index>223</index>
    <label>red</label>
  </sThought>
  <sThought>
    <index>224</index>
    <label>unl_e53e4a99</label>
    <source>223</source>
    <linkType>2</linkType>
    <target>160</target>
  </sThought>
  <sThought>
    <index>225</index>
    <label>orange</label>
  </sThought>
  <sThought>
    <index>226</index>
    <label>unl_92d8b118</label>
    <source>225</source>
    <linkType>2</linkType>
    <target>160</target>
  </sThought>
  <sThought>
    <index>227</index>
    <label>yellow</label>
  </sThought>
  <sThought>
    <index>228</index>
    <label>unl_d95ae8c7</label>
    <source>227</source>
    <linkType>2</linkType>
    <target>160</target>
  </sThought>
  <sThought>
    <index>229</index>
    <label>green</label>
  </sThought>
  <sThought>
    <index>230</index>
    <label>unl_9a259b38</label>
    <source>229</source>
    <linkType>2</linkType>
    <target>160</target>
  </sThought>
  <sThought>
    <index>231</index>
    <label>blue</label>
  </sThought>
  <sThought>
    <index>232</index>
    <label>unl_d282094c</label>
    <source>231</source>
    <linkType>2</linkType>
    <target>160</target>
  </sThought>
  <sThought>
    <index>233</index>
    <label>purple</label>
  </sThought>
  <sThought>
    <index>234</index>
    <label>unl_29a3caed</label>
    <source>233</source>
    <linkType>2</linkType>
    <target>160</target>
  </sThought>
  <sThought>
    <index>235</index>
    <label>brown</label>
  </sThought>
  <sThought>
    <index>236</index>
    <label>unl_c1721441</label>
    <source>235</source>
    <linkType>2</linkType>
    <target>160</target>
  </sThought>
  <sThought>
    <index>237</index>
    <label>pink</label>
  </sThought>
  <sThought>
    <index>238</index>
    <label>unl_d539ab4b</label>
    <source>237</source>
    <linkType>2</linkType>
    <target>160</target>
  </sThought>
  <sThought>
    <index>239</index>
    <label>black</label>
  </sThought>
  <sThought>
    <index>240</index>
    <label>unl_f31aaeb9</label>
    <source>239</source>
    <linkType>2</linkType>
    <target>160</target>
  </sThought>
  <sThought>
    <index>241</index>
    <label>white</label>
  </sThought>
  <sThought>
    <index>242</index>
    <label>unl_9088c247</label>
    <source>241</source>
    <linkType>2</linkType>
    <target>160</target>
  </sThought>
  <sThought>
    <index>243</index>
    <label>gray</label>
  </sThought>
  <sThought>
    <index>244</index>
    <label>unl_8f275144</label>
    <source>243</source>
    <linkType>2</linkType>
    <target>160</target>
  </sThought>
  <sThought>
    <index>245</index>
    <label>unl_7c60bdb1</label>
    <source>160</source>
    <linkType>96</linkType>
    <target>178</target>
  </sThought>
  <sThought>
    <index>246</index>
    <label>digit</label>
  </sThought>
  <sThought>
    <index>247</index>
    <label>unl_c9e13979</label>
    <source>246</source>
    <linkType>2</linkType>
    <target>162</target>
  </sThought>
  <sThought>
    <index>248</index>
    <label>some</label>
  </sThought>
  <sThought>
    <index>249</index>
    <label>unl_7c76df27</label>
    <source>248</source>
    <linkType>2</linkType>
    <target>162</target>
  </sThought>
  <sThought>
    <index>250</index>
    <label>many</label>
  </sThought>
  <sThought>
    <index>251</index>
    <label>unl_5ac20f2d</label>
    <source>250</source>
    <linkType>2</linkType>
    <target>162</target>
  </sThought>
  <sThought>
    <index>252</index>
    <label>none</label>
  </sThought>
  <sThought>
    <index>253</index>
    <label>unl_948def07</label>
    <source>252</source>
    <linkType>2</linkType>
    <target>162</target>
  </sThought>
  <sThought>
    <index>254</index>
    <label>pi</label>
  </sThought>
  <sThought>
    <index>255</index>
    <label>unl_dd958fe3</label>
    <source>254</source>
    <linkType>2</linkType>
    <target>162</target>
  </sThought>
  <sThought>
    <index>256</index>
    <label>unl_e763dd2a</label>
    <source>162</source>
    <linkType>96</linkType>
    <target>178</target>
  </sThought>
  <sThought>
    <index>257</index>
    <label>p:is|a</label>
  </sThought>
  <sThought>
    <index>258</index>
    <label>unl_5f0d5020</label>
    <source>257</source>
    <linkType>2</linkType>
    <target>164</target>
  </sThought>
  <sThought>
    <index>259</index>
    <label>p:es|un</label>
  </sThought>
  <sThought>
    <index>260</index>
    <label>unl_8e193109</label>
    <source>259</source>
    <linkType>2</linkType>
    <target>164</target>
  </sThought>
  <sThought>
    <index>261</index>
    <label>w:no</label>
  </sThought>
  <sThought>
    <index>262</index>
    <label>unl_2603e506</label>
    <source>261</source>
    <linkType>2</linkType>
    <target>166</target>
  </sThought>
  <sThought>
    <index>263</index>
    <label>w:not</label>
  </sThought>
  <sThought>
    <index>264</index>
    <label>unl_e0d7d65b</label>
    <source>263</source>
    <linkType>2</linkType>
    <target>166</target>
  </sThought>
  <sThought>
    <index>265</index>
    <label>w:can</label>
  </sThought>
  <sThought>
    <index>266</index>
    <label>unl_f1196303</label>
    <source>265</source>
    <linkType>2</linkType>
    <target>166</target>
  </sThought>
  <sThought>
    <index>267</index>
    <label>w:is</label>
  </sThought>
  <sThought>
    <index>268</index>
    <label>unl_03fc633d</label>
    <source>267</source>
    <linkType>2</linkType>
    <target>166</target>
  </sThought>
  <sThought>
    <index>269</index>
    <label>w:a</label>
  </sThought>
  <sThought>
    <index>270</index>
    <label>unl_24ff500a</label>
    <source>269</source>
    <linkType>2</linkType>
    <target>166</target>
  </sThought>
  <sThought>
    <index>271</index>
    <label>w:es</label>
  </sThought>
  <sThought>
    <index>272</index>
    <label>unl_fda9f6ea</label>
    <source>271</source>
    <linkType>2</linkType>
    <target>168</target>
  </sThought>
  <sThought>
    <index>273</index>
    <label>w:un</label>
  </sThought>
  <sThought>
    <index>274</index>
    <label>unl_0d12dfc6</label>
    <source>273</source>
    <linkType>2</linkType>
    <target>168</target>
  </sThought>
  <sThought>
    <index>275</index>
    <label>unl_723dde76</label>
    <source>198</source>
    <linkType>134</linkType>
    <target>196</target>
  </sThought>
  <sThought>
    <index>276</index>
    <label>unl_1e5212f2</label>
    <source>216</source>
    <linkType>96</linkType>
    <target>97</target>
  </sThought>
  <sThought>
    <index>277</index>
    <label>unl_fc9587a7</label>
    <source>218</source>
    <linkType>134</linkType>
    <target>216</target>
  </sThought>
  <sThought>
    <index>278</index>
    <label>unl_44dabeae</label>
    <source>220</source>
    <linkType>96</linkType>
    <target>183</target>
  </sThought>
  <sThought>
    <index>279</index>
    <label>-</label>
  </sThought>
  <sThought>
    <index>280</index>
    <label>unl_ed012a50</label>
    <source>279</source>
    <linkType>2</linkType>
    <target>246</target>
  </sThought>
  <sThought>
    <index>281</index>
    <label>.</label>
  </sThought>
  <sThought>
    <index>282</index>
    <label>unl_02349753</label>
    <source>281</source>
    <linkType>2</linkType>
    <target>246</target>
  </sThought>
  <sThought>
    <index>283</index>
    <label>0</label>
  </sThought>
  <sThought>
    <index>284</index>
    <label>unl_518fde3e</label>
    <source>283</source>
    <linkType>2</linkType>
    <target>246</target>
  </sThought>
  <sThought>
    <index>285</index>
    <label>1</label>
  </sThought>
  <sThought>
    <index>286</index>
    <label>unl_832ec5e2</label>
    <source>285</source>
    <linkType>2</linkType>
    <target>246</target>
  </sThought>
  <sThought>
    <index>287</index>
    <label>2</label>
  </sThought>
  <sThought>
    <index>288</index>
    <label>unl_c9b2f767</label>
    <source>287</source>
    <linkType>2</linkType>
    <target>246</target>
  </sThought>
  <sThought>
    <index>289</index>
    <label>3</label>
  </sThought>
  <sThought>
    <index>290</index>
    <label>unl_33c52e29</label>
    <source>289</source>
    <linkType>2</linkType>
    <target>246</target>
  </sThought>
  <sThought>
    <index>291</index>
    <label>4</label>
  </sThought>
  <sThought>
    <index>292</index>
    <label>unl_28015bc7</label>
    <source>291</source>
    <linkType>2</linkType>
    <target>246</target>
  </sThought>
  <sThought>
    <index>293</index>
    <label>5</label>
  </sThought>
  <sThought>
    <index>294</index>
    <label>unl_fdc38c5d</label>
    <source>293</source>
    <linkType>2</linkType>
    <target>246</target>
  </sThought>
  <sThought>
    <index>295</index>
    <label>6</label>
  </sThought>
  <sThought>
    <index>296</index>
    <label>unl_3749c5b9</label>
    <source>295</source>
    <linkType>2</linkType>
    <target>246</target>
  </sThought>
  <sThought>
    <index>297</index>
    <label>7</label>
  </sThought>
  <sThought>
    <index>298</index>
    <label>unl_6dbe3d11</label>
    <source>297</source>
    <linkType>2</linkType>
    <target>246</target>
  </sThought>
  <sThought>
    <index>299</index>
    <label>8</label>
  </sThought>
  <sThought>
    <index>300</index>
    <label>unl_195cd2eb</label>
    <source>299</source>
    <linkType>2</linkType>
    <target>246</target>
  </sThought>
  <sThought>
    <index>301</index>
    <label>9</label>
  </sThought>
  <sThought>
    <index>302</index>
    <label>unl_b9f0a8b9</label>
    <source>301</source>
    <linkType>2</linkType>
    <target>246</target>
  </sThought>
  <sThought>
    <index>303</index>
    <label>digit-seq0</label>
  </sThought>
  <sThought>
    <index>304</index>
    <label>unl_f182e995</label>
    <source>246</source>
    <linkType>214</linkType>
    <target>303</target>
  </sThought>
  <sThought>
    <index>305</index>
    <label>pi-seq0</label>
  </sThought>
  <sThought>
    <index>306</index>
    <label>unl_5d7e0573</label>
    <source>254</source>
    <linkType>174</linkType>
    <target>305</target>
  </sThought>
  <sThought>
    <index>307</index>
    <label>unl_f3b10c98</label>
    <source>257</source>
    <linkType>156</linkType>
    <target>2</target>
  </sThought>
  <sThought>
    <index>308</index>
    <label>p:is|a-seq0</label>
  </sThought>
  <sThought>
    <index>309</index>
    <label>unl_0c24c190</label>
    <source>257</source>
    <linkType>144</linkType>
    <target>308</target>
  </sThought>
  <sThought>
    <index>310</index>
    <label>unl_2ba789b8</label>
    <source>259</source>
    <linkType>156</linkType>
    <target>2</target>
  </sThought>
  <sThought>
    <index>311</index>
    <label>p:es|un-seq0</label>
  </sThought>
  <sThought>
    <index>312</index>
    <label>unl_37991dd3</label>
    <source>259</source>
    <linkType>144</linkType>
    <target>311</target>
  </sThought>
  <sThought>
    <index>313</index>
    <label>unl_12607f5f</label>
    <source>261</source>
    <linkType>156</linkType>
    <target>210</target>
  </sThought>
  <sThought>
    <index>314</index>
    <label>unl_c3c9aa99</label>
    <source>263</source>
    <linkType>156</linkType>
    <target>208</target>
  </sThought>
  <sThought>
    <index>315</index>
    <label>unl_2d08b5aa</label>
    <source>265</source>
    <linkType>156</linkType>
    <target>140</target>
  </sThought>
  <sThought>
    <index>316</index>
    <label>unl_a6f42ed6</label>
    <source>285</source>
    <linkType>216</linkType>
    <target>283</target>
  </sThought>
  <sThought>
    <index>317</index>
    <label>unl_87a1b7a4</label>
    <source>287</source>
    <linkType>216</linkType>
    <target>285</target>
  </sThought>
  <sThought>
    <index>318</index>
    <label>unl_2f252dd6</label>
    <source>289</source>
    <linkType>216</linkType>
    <target>287</target>
  </sThought>
  <sThought>
    <index>319</index>
    <label>unl_aff01bfb</label>
    <source>291</source>
    <linkType>216</linkType>
    <target>289</target>
  </sThought>
  <sThought>
    <index>320</index>
    <label>unl_0a405665</label>
    <source>293</source>
    <linkType>216</linkType>
    <target>291</target>
  </sThought>
  <sThought>
    <index>321</index>
    <label>unl_1fcec058</label>
    <source>295</source>
    <linkType>216</linkType>
    <target>293</target>
  </sThought>
  <sThought>
    <index>322</index>
    <label>unl_03c5ec04</label>
    <source>297</source>
    <linkType>216</linkType>
    <target>295</target>
  </sThought>
  <sThought>
    <index>323</index>
    <label>unl_84af2504</label>
    <source>299</source>
    <linkType>216</linkType>
    <target>297</target>
  </sThought>
  <sThought>
    <index>324</index>
    <label>unl_31c26fa7</label>
    <source>301</source>
    <linkType>216</linkType>
    <target>299</target>
  </sThought>
  <sThought>
    <index>325</index>
    <label>unl_03352656</label>
    <source>303</source>
    <linkType>202</linkType>
    <target>283</target>
  </sThought>
  <sThought>
    <index>326</index>
    <label>unl_663083be</label>
    <source>303</source>
    <linkType>212</linkType>
    <target>303</target>
  </sThought>
  <sThought>
    <index>327</index>
    <label>digit-seq1</label>
  </sThought>
  <sThought>
    <index>328</index>
    <label>unl_7395906a</label>
    <source>303</source>
    <linkType>200</linkType>
    <target>327</target>
  </sThought>
  <sThought>
    <index>329</index>
    <label>unl_3206e4cd</label>
    <source>305</source>
    <linkType>202</linkType>
    <target>289</target>
  </sThought>
  <sThought>
    <index>330</index>
    <label>unl_07629c8c</label>
    <source>305</source>
    <linkType>212</linkType>
    <target>305</target>
  </sThought>
  <sThought>
    <index>331</index>
    <label>pi-seq1</label>
  </sThought>
  <sThought>
    <index>332</index>
    <label>unl_b5d5d48d</label>
    <source>305</source>
    <linkType>200</linkType>
    <target>331</target>
  </sThought>
  <sThought>
    <index>333</index>
    <label>unl_1222c486</label>
    <source>308</source>
    <linkType>202</linkType>
    <target>267</target>
  </sThought>
  <sThought>
    <index>334</index>
    <label>unl_ef422729</label>
    <source>308</source>
    <linkType>212</linkType>
    <target>308</target>
  </sThought>
  <sThought>
    <index>335</index>
    <label>p:is|a-seq1</label>
  </sThought>
  <sThought>
    <index>336</index>
    <label>unl_7d421f60</label>
    <source>308</source>
    <linkType>200</linkType>
    <target>335</target>
  </sThought>
  <sThought>
    <index>337</index>
    <label>unl_54ea4f85</label>
    <source>311</source>
    <linkType>202</linkType>
    <target>271</target>
  </sThought>
  <sThought>
    <index>338</index>
    <label>unl_3f874f5e</label>
    <source>311</source>
    <linkType>212</linkType>
    <target>311</target>
  </sThought>
  <sThought>
    <index>339</index>
    <label>p:es|un-seq1</label>
  </sThought>
  <sThought>
    <index>340</index>
    <label>unl_3ceb1057</label>
    <source>311</source>
    <linkType>200</linkType>
    <target>339</target>
  </sThought>
  <sThought>
    <index>341</index>
    <label>unl_75e42e9a</label>
    <source>327</source>
    <linkType>212</linkType>
    <target>303</target>
  </sThought>
  <sThought>
    <index>342</index>
    <label>unl_a6e1deae</label>
    <source>327</source>
    <linkType>202</linkType>
    <target>285</target>
  </sThought>
  <sThought>
    <index>343</index>
    <label>digit-seq2</label>
  </sThought>
  <sThought>
    <index>344</index>
    <label>unl_039aa0c6</label>
    <source>327</source>
    <linkType>200</linkType>
    <target>343</target>
  </sThought>
  <sThought>
    <index>345</index>
    <label>unl_af22282f</label>
    <source>343</source>
    <linkType>212</linkType>
    <target>303</target>
  </sThought>
  <sThought>
    <index>346</index>
    <label>unl_98644b0c</label>
    <source>343</source>
    <linkType>202</linkType>
    <target>287</target>
  </sThought>
  <sThought>
    <index>347</index>
    <label>digit-seq3</label>
  </sThought>
  <sThought>
    <index>348</index>
    <label>unl_04fb34ad</label>
    <source>343</source>
    <linkType>200</linkType>
    <target>347</target>
  </sThought>
  <sThought>
    <index>349</index>
    <label>unl_8329b08e</label>
    <source>347</source>
    <linkType>212</linkType>
    <target>303</target>
  </sThought>
  <sThought>
    <index>350</index>
    <label>unl_036c4983</label>
    <source>347</source>
    <linkType>202</linkType>
    <target>289</target>
  </sThought>
  <sThought>
    <index>351</index>
    <label>digit-seq4</label>
  </sThought>
  <sThought>
    <index>352</index>
    <label>unl_8ead3035</label>
    <source>347</source>
    <linkType>200</linkType>
    <target>351</target>
  </sThought>
  <sThought>
    <index>353</index>
    <label>unl_0bf108b2</label>
    <source>351</source>
    <linkType>212</linkType>
    <target>303</target>
  </sThought>
  <sThought>
    <index>354</index>
    <label>unl_1d54b880</label>
    <source>351</source>
    <linkType>202</linkType>
    <target>291</target>
  </sThought>
  <sThought>
    <index>355</index>
    <label>digit-seq5</label>
  </sThought>
  <sThought>
    <index>356</index>
    <label>unl_ae839166</label>
    <source>351</source>
    <linkType>200</linkType>
    <target>355</target>
  </sThought>
  <sThought>
    <index>357</index>
    <label>unl_3428ed60</label>
    <source>355</source>
    <linkType>212</linkType>
    <target>303</target>
  </sThought>
  <sThought>
    <index>358</index>
    <label>unl_70a1c74a</label>
    <source>355</source>
    <linkType>202</linkType>
    <target>293</target>
  </sThought>
  <sThought>
    <index>359</index>
    <label>digit-seq6</label>
  </sThought>
  <sThought>
    <index>360</index>
    <label>unl_c3110f63</label>
    <source>355</source>
    <linkType>200</linkType>
    <target>359</target>
  </sThought>
  <sThought>
    <index>361</index>
    <label>unl_5a918561</label>
    <source>359</source>
    <linkType>212</linkType>
    <target>303</target>
  </sThought>
  <sThought>
    <index>362</index>
    <label>unl_3c041e66</label>
    <source>359</source>
    <linkType>202</linkType>
    <target>295</target>
  </sThought>
  <sThought>
    <index>363</index>
    <label>digit-seq7</label>
  </sThought>
  <sThought>
    <index>364</index>
    <label>unl_d4f2beca</label>
    <source>359</source>
    <linkType>200</linkType>
    <target>363</target>
  </sThought>
  <sThought>
    <index>365</index>
    <label>unl_58c1129c</label>
    <source>363</source>
    <linkType>212</linkType>
    <target>303</target>
  </sThought>
  <sThought>
    <index>366</index>
    <label>unl_af27dfa8</label>
    <source>363</source>
    <linkType>202</linkType>
    <target>297</target>
  </sThought>
  <sThought>
    <index>367</index>
    <label>digit-seq8</label>
  </sThought>
  <sThought>
    <index>368</index>
    <label>unl_c69a86b9</label>
    <source>363</source>
    <linkType>200</linkType>
    <target>367</target>
  </sThought>
  <sThought>
    <index>369</index>
    <label>unl_07c1c830</label>
    <source>367</source>
    <linkType>212</linkType>
    <target>303</target>
  </sThought>
  <sThought>
    <index>370</index>
    <label>unl_b75a9178</label>
    <source>367</source>
    <linkType>202</linkType>
    <target>299</target>
  </sThought>
  <sThought>
    <index>371</index>
    <label>digit-seq9</label>
  </sThought>
  <sThought>
    <index>372</index>
    <label>unl_1e90cbe1</label>
    <source>367</source>
    <linkType>200</linkType>
    <target>371</target>
  </sThought>
  <sThought>
    <index>373</index>
    <label>unl_3fb54510</label>
    <source>371</source>
    <linkType>212</linkType>
    <target>303</target>
  </sThought>
  <sThought>
    <index>374</index>
    <label>unl_6e2e7d7e</label>
    <source>371</source>
    <linkType>202</linkType>
    <target>301</target>
  </sThought>
  <sThought>
    <index>375</index>
    <label>unl_2c054525</label>
    <source>331</source>
    <linkType>212</linkType>
    <target>305</target>
  </sThought>
  <sThought>
    <index>376</index>
    <label>unl_5f8381cc</label>
    <source>331</source>
    <linkType>202</linkType>
    <target>281</target>
  </sThought>
  <sThought>
    <index>377</index>
    <label>pi-seq2</label>
  </sThought>
  <sThought>
    <index>378</index>
    <label>unl_65e50d45</label>
    <source>331</source>
    <linkType>200</linkType>
    <target>377</target>
  </sThought>
  <sThought>
    <index>379</index>
    <label>unl_c25b170e</label>
    <source>377</source>
    <linkType>212</linkType>
    <target>305</target>
  </sThought>
  <sThought>
    <index>380</index>
    <label>unl_cfc23ef4</label>
    <source>377</source>
    <linkType>202</linkType>
    <target>285</target>
  </sThought>
  <sThought>
    <index>381</index>
    <label>pi-seq3</label>
  </sThought>
  <sThought>
    <index>382</index>
    <label>unl_f106b1ad</label>
    <source>377</source>
    <linkType>200</linkType>
    <target>381</target>
  </sThought>
  <sThought>
    <index>383</index>
    <label>unl_cd9cd511</label>
    <source>381</source>
    <linkType>212</linkType>
    <target>305</target>
  </sThought>
  <sThought>
    <index>384</index>
    <label>unl_7566e4ff</label>
    <source>381</source>
    <linkType>202</linkType>
    <target>291</target>
  </sThought>
  <sThought>
    <index>385</index>
    <label>pi-seq4</label>
  </sThought>
  <sThought>
    <index>386</index>
    <label>unl_e0a4bf6c</label>
    <source>381</source>
    <linkType>200</linkType>
    <target>385</target>
  </sThought>
  <sThought>
    <index>387</index>
    <label>unl_1ae28f88</label>
    <source>385</source>
    <linkType>212</linkType>
    <target>305</target>
  </sThought>
  <sThought>
    <index>388</index>
    <label>unl_e5ef3642</label>
    <source>385</source>
    <linkType>202</linkType>
    <target>285</target>
  </sThought>
  <sThought>
    <index>389</index>
    <label>pi-seq5</label>
  </sThought>
  <sThought>
    <index>390</index>
    <label>unl_3fd4b7c8</label>
    <source>385</source>
    <linkType>200</linkType>
    <target>389</target>
  </sThought>
  <sThought>
    <index>391</index>
    <label>unl_9c5fc8ea</label>
    <source>389</source>
    <linkType>212</linkType>
    <target>305</target>
  </sThought>
  <sThought>
    <index>392</index>
    <label>unl_98954b32</label>
    <source>389</source>
    <linkType>202</linkType>
    <target>293</target>
  </sThought>
  <sThought>
    <index>393</index>
    <label>pi-seq6</label>
  </sThought>
  <sThought>
    <index>394</index>
    <label>unl_b543d1fa</label>
    <source>389</source>
    <linkType>200</linkType>
    <target>393</target>
  </sThought>
  <sThought>
    <index>395</index>
    <label>unl_5c8ce20b</label>
    <source>393</source>
    <linkType>212</linkType>
    <target>305</target>
  </sThought>
  <sThought>
    <index>396</index>
    <label>unl_27291812</label>
    <source>393</source>
    <linkType>202</linkType>
    <target>301</target>
  </sThought>
  <sThought>
    <index>397</index>
    <label>unl_f8e6bf4a</label>
    <source>335</source>
    <linkType>212</linkType>
    <target>308</target>
  </sThought>
  <sThought>
    <index>398</index>
    <label>unl_4d0f30f2</label>
    <source>335</source>
    <linkType>202</linkType>
    <target>269</target>
  </sThought>
  <sThought>
    <index>399</index>
    <label>unl_1c888335</label>
    <source>339</source>
    <linkType>212</linkType>
    <target>311</target>
  </sThought>
  <sThought>
    <index>400</index>
    <label>unl_a171892b</label>
    <source>339</source>
    <linkType>202</linkType>
    <target>273</target>
  </sThought>
</ArrayOfSThought>